VexV5Interpreter/__init__.py
VexV5Interpreter/main.py
VexV5Interpreter/graphics/robot-icon.png
VexV5Interpreter/graphics/tile-green.png
VexV5Interpreter/graphics/tile-red.png
VexV5Interpreter/graphics/tile-yellow.png
vexv5interpreter-0.1.6.dist-info/METADATA
vexv5interpreter-0.1.6.dist-info/WHEEL
vexv5interpreter-0.1.6.dist-info/RECORD
