Metadata-Version: 2.1
Name: VexV5Interpreter
Version: 0.1.6
Summary: This project allows for the running of Vex V5 Python Code without a robot present. 
Project-URL: Homepage, https://github.com/CrispierVase/Vex-V5-Python-Interpreter
Project-URL: Bug Tracker, https://github.com/CrispierVase/Vex-V5-Python-Interpreter/issues
Author-email: Bryson Smith <brysonisaiah0115@yahoo.com>
Classifier: Operating System :: OS Independent
Classifier: Programming Language :: Python :: 3
Requires-Python: >=3.7
Requires-Dist: pygame
